{
  "AAVE/USDT:USDT": 291.69,
  "ADA/USDT:USDT": 0.5883,
  "AI16Z/USDT:USDT": 0.1498,
  "AIXBT/USDT:USDT": 0.12519,
  "ALGO/USDT:USDT": 0.1787,
  "APT/USDT:USDT": 4.4118,
  "ARB/USDT:USDT": 0.3353,
  "AR/USDT:USDT": 5.221,
  "ATOM/USDT:USDT": 4.108,
  "AVAX/USDT:USDT": 18.164,
  "BCH/USDT:USDT": 503.11,
  "BERA/USDT:USDT": 1.673,
  "BNB/USDT:USDT": 662.08,
  "CRV/USDT:USDT": 0.5164,
  "DOGE/USDT:USDT": 0.17141,
  "DOT/USDT:USDT": 3.429,
  "EIGEN/USDT:USDT": 1.1352,
  "ENA/USDT:USDT": 0.2623,
  "ETC/USDT:USDT": 16.871,
  "ETH/USDT:USDT": 2605.63,
  "FARTCOIN/USDT:USDT": 1.0459,
  "FLOKI/USDT:USDT": 8.969e-05,
  "FXS/USDT:USDT": 2.0,
  "GOAT/USDT:USDT": 0.09693,
  "GRASS/USDT:USDT": 1.1694,
  "HBAR/USDT:USDT": 0.16089,
  "HYPE/USDT:USDT": 38.91,
  "INJ/USDT:USDT": 10.326,
  "IP/USDT:USDT": 3.0,
  "JTO/USDT:USDT": 1.8432,
  "JUP/USDT:USDT": 0.4288,
  "KAITO/USDT:USDT": 1.4632,
  "LDO/USDT:USDT": 0.715,
  "LINK/USDT:USDT": 13.914,
  "LTC/USDT:USDT": 87.67,
  "MEW/USDT:USDT": 0.00272,
  "MKR/USDT:USDT": 1909.5,
  "MOODENG/USDT:USDT": 0.17684,
  "MOVE/USDT:USDT": 0.1458,
  "NEAR/USDT:USDT": 2.212,
  "ONDO/USDT:USDT": 0.7972,
  "OP/USDT:USDT": 0.5415,
  "ORDI/USDT:USDT": 7.551,
  "PENDLE/USDT:USDT": 3.4134,
  "PENGU/USDT:USDT": 0.0148,
  "PEPE/USDT:USDT": 1.0073e-05,
  "PNUT/USDT:USDT": 0.2211,
  "POL/USDT:USDT": 0.19471,
  "POPCAT/USDT:USDT": 0.2845,
  "RENDER/USDT:USDT": 3.203,
  "RUNE/USDT:USDT": 1.353,
  "SEI/USDT:USDT": 0.2566,
  "SHIB/USDT:USDT": 1.1836e-05,
  "SOL/USDT:USDT": 151.95,
  "SPX/USDT:USDT": 1.3349,
  "STX/USDT:USDT": 0.6518,
  "SUI/USDT:USDT": 2.8954,
  "TAO/USDT:USDT": 318.7,
  "TIA/USDT:USDT": 1.569,
  "TRUMP/USDT:USDT": 0.128,
  "TRX/USDT:USDT": 0.28737,
  "ZETA/USDT:USDT": 0.177,
  "ZRO/USDT:USDT": 1.797
}