{
  "AAVE/USDT:USDT": 262.67,
  "ADA/USDT:USDT": 0.6797,
  "AI16Z/USDT:USDT": 0.2113,
  "AIXBT/USDT:USDT": 0.17757,
  "ALGO/USDT:USDT": 0.1916,
  "APT/USDT:USDT": 4.8089,
  "ARB/USDT:USDT": 0.3568,
  "AR/USDT:USDT": 6.492,
  "ATOM/USDT:USDT": 4.329,
  "AVAX/USDT:USDT": 20.269,
  "BCH/USDT:USDT": 403.02,
  "BERA/USDT:USDT": 2.442,
  "BNB/USDT:USDT": 668.14,
  "CRV/USDT:USDT": 0.6357,
  "DOGE/USDT:USDT": 0.18951,
  "DOT/USDT:USDT": 4.045,
  "EIGEN/USDT:USDT": 1.4449,
  "ENA/USDT:USDT": 0.3141,
  "ETC/USDT:USDT": 17.341,
  "ETH/USDT:USDT": 2611.0,
  "FARTCOIN/USDT:USDT": 0.9013,
  "FLOKI/USDT:USDT": 8.243e-05,
  "FXS/USDT:USDT": 2.923,
  "GOAT/USDT:USDT": 0.11992,
  "GRASS/USDT:USDT": 1.8774,
  "HBAR/USDT:USDT": 0.16778,
  "HYPE/USDT:USDT": 34.96,
  "INJ/USDT:USDT": 12.239,
  "IP/USDT:USDT": 4.056,
  "JTO/USDT:USDT": 1.8418,
  "JUP/USDT:USDT": 0.5128,
  "KAITO/USDT:USDT": 1.6835,
  "LDO/USDT:USDT": 0.8647,
  "LINK/USDT:USDT": 13.84,
  "LTC/USDT:USDT": 87.82,
  "MEW/USDT:USDT": 0.003183,
  "MKR/USDT:USDT": 1780.3,
  "MOODENG/USDT:USDT": 0.19268,
  "MOVE/USDT:USDT": 0.1436,
  "NEAR/USDT:USDT": 2.459,
  "ONDO/USDT:USDT": 0.8257,
  "OP/USDT:USDT": 0.6335,
  "ORDI/USDT:USDT": 8.749,
  "PENDLE/USDT:USDT": 4.0931,
  "PENGU/USDT:USDT": 0.00996,
  "PEPE/USDT:USDT": 1.1831e-05,
  "PNUT/USDT:USDT": 0.259,
  "POL/USDT:USDT": 0.21659,
  "POPCAT/USDT:USDT": 0.352,
  "RENDER/USDT:USDT": 3.774,
  "RUNE/USDT:USDT": 1.64,
  "SEI/USDT:USDT": 0.1935,
  "SHIB/USDT:USDT": 1.2858e-05,
  "SOL/USDT:USDT": 152.83,
  "SPX/USDT:USDT": 1.1299,
  "STX/USDT:USDT": 0.756,
  "SUI/USDT:USDT": 3.1729,
  "TAO/USDT:USDT": 378.8,
  "TIA/USDT:USDT": 2.167,
  "TRUMP/USDT:USDT": 0.1643,
  "TRX/USDT:USDT": 0.27316,
  "ZETA/USDT:USDT": 0.2225,
  "ZRO/USDT:USDT": 2.236
}