{
  "AAVE/USDT:USDT": 263.51,
  "ADA/USDT:USDT": 0.6667,
  "AI16Z/USDT:USDT": 0.2123,
  "AIXBT/USDT:USDT": 0.17441,
  "ALGO/USDT:USDT": 0.1904,
  "APT/USDT:USDT": 4.7814,
  "ARB/USDT:USDT": 0.3572,
  "AR/USDT:USDT": 6.448,
  "ATOM/USDT:USDT": 4.265,
  "AVAX/USDT:USDT": 20.148,
  "BCH/USDT:USDT": 400.43,
  "BERA/USDT:USDT": 2.435,
  "BNB/USDT:USDT": 664.25,
  "CRV/USDT:USDT": 0.6513,
  "DOGE/USDT:USDT": 0.18819,
  "DOT/USDT:USDT": 4.005,
  "EIGEN/USDT:USDT": 1.4977,
  "ENA/USDT:USDT": 0.3151,
  "ETC/USDT:USDT": 17.183,
  "ETH/USDT:USDT": 2602.31,
  "FARTCOIN/USDT:USDT": 0.9471,
  "FLOKI/USDT:USDT": 8.193e-05,
  "FXS/USDT:USDT": 2.978,
  "GOAT/USDT:USDT": 0.12023,
  "GRASS/USDT:USDT": 1.9274,
  "HBAR/USDT:USDT": 0.16685,
  "HYPE/USDT:USDT": 34.9,
  "INJ/USDT:USDT": 12.23,
  "IP/USDT:USDT": 4.028,
  "JTO/USDT:USDT": 1.8469,
  "JUP/USDT:USDT": 0.5238,
  "KAITO/USDT:USDT": 1.6735,
  "LDO/USDT:USDT": 0.8918,
  "LINK/USDT:USDT": 13.772,
  "LTC/USDT:USDT": 87.95,
  "MEW/USDT:USDT": 0.003178,
  "MKR/USDT:USDT": 1784.2,
  "MOODENG/USDT:USDT": 0.19473,
  "MOVE/USDT:USDT": 0.1428,
  "NEAR/USDT:USDT": 2.435,
  "ONDO/USDT:USDT": 0.8292,
  "OP/USDT:USDT": 0.6295,
  "ORDI/USDT:USDT": 8.722,
  "PENDLE/USDT:USDT": 4.1105,
  "PENGU/USDT:USDT": 0.00995,
  "PEPE/USDT:USDT": 1.1875e-05,
  "PNUT/USDT:USDT": 0.2573,
  "POL/USDT:USDT": 0.21326,
  "POPCAT/USDT:USDT": 0.3507,
  "RENDER/USDT:USDT": 3.742,
  "RUNE/USDT:USDT": 1.618,
  "SEI/USDT:USDT": 0.193,
  "SHIB/USDT:USDT": 1.278e-05,
  "SOL/USDT:USDT": 154.35,
  "SPX/USDT:USDT": 1.091,
  "STX/USDT:USDT": 0.7522,
  "SUI/USDT:USDT": 3.1879,
  "TAO/USDT:USDT": 381.5,
  "TIA/USDT:USDT": 2.143,
  "TRUMP/USDT:USDT": 0.1738,
  "TRX/USDT:USDT": 0.27341,
  "ZETA/USDT:USDT": 0.2176,
  "ZRO/USDT:USDT": 2.205
}