{
  "AAVE/USDT:USDT": 304.69,
  "ADA/USDT:USDT": 0.8417,
  "AI16Z/USDT:USDT": 0.1611,
  "AIXBT/USDT:USDT": 0.15175,
  "ALGO/USDT:USDT": 0.2847,
  "APT/USDT:USDT": 4.9317,
  "ARB/USDT:USDT": 0.4707,
  "AR/USDT:USDT": 7.975,
  "ATOM/USDT:USDT": 4.869,
  "AVAX/USDT:USDT": 26.531,
  "BCH/USDT:USDT": 591.0,
  "BERA/USDT:USDT": 2.295,
  "BNB/USDT:USDT": 842.4,
  "CRV/USDT:USDT": 1.0113,
  "DOGE/USDT:USDT": 0.24448,
  "DOT/USDT:USDT": 4.273,
  "EIGEN/USDT:USDT": 1.4523,
  "ENA/USDT:USDT": 0.6888,
  "ETC/USDT:USDT": 23.459,
  "ETH/USDT:USDT": 3900.35,
  "FARTCOIN/USDT:USDT": 1.3832,
  "FLOKI/USDT:USDT": 0.00013177,
  "FXS/USDT:USDT": 3.56,
  "GOAT/USDT:USDT": 0.12518,
  "GRASS/USDT:USDT": 0.9384,
  "HBAR/USDT:USDT": 0.28505,
  "HYPE/USDT:USDT": 44.22,
  "INJ/USDT:USDT": 15.582,
  "IP/USDT:USDT": 5.659,
  "JTO/USDT:USDT": 2.079,
  "JUP/USDT:USDT": 0.6116,
  "KAITO/USDT:USDT": 1.3673,
  "LDO/USDT:USDT": 1.1594,
  "LINK/USDT:USDT": 19.317,
  "LTC/USDT:USDT": 115.2,
  "MEW/USDT:USDT": 0.00372,
  "MKR/USDT:USDT": 2385.4,
  "MOODENG/USDT:USDT": 0.20801,
  "MOVE/USDT:USDT": 0.153,
  "NEAR/USDT:USDT": 2.98,
  "ONDO/USDT:USDT": 1.0675,
  "OP/USDT:USDT": 0.8021,
  "ORDI/USDT:USDT": 11.495,
  "PENDLE/USDT:USDT": 4.5484,
  "PENGU/USDT:USDT": 0.04255,
  "PEPE/USDT:USDT": 1.2956e-05,
  "PNUT/USDT:USDT": 0.2864,
  "POL/USDT:USDT": 0.24151,
  "POPCAT/USDT:USDT": 0.3875,
  "RENDER/USDT:USDT": 4.387,
  "RUNE/USDT:USDT": 1.515,
  "SEI/USDT:USDT": 0.3518,
  "SHIB/USDT:USDT": 1.4197e-05,
  "SOL/USDT:USDT": 192.87,
  "SPX/USDT:USDT": 2.2477,
  "STX/USDT:USDT": 0.8584,
  "SUI/USDT:USDT": 4.2963,
  "TAO/USDT:USDT": 431.9,
  "TIA/USDT:USDT": 2.09,
  "TRUMP/USDT:USDT": 0.1569,
  "TRX/USDT:USDT": 0.32039,
  "ZETA/USDT:USDT": 0.2302,
  "ZRO/USDT:USDT": 2.035
}