{
  "AAVE/USDT:USDT": 296.45,
  "ADA/USDT:USDT": 0.8225,
  "AI16Z/USDT:USDT": 0.1523,
  "AIXBT/USDT:USDT": 0.14924,
  "ALGO/USDT:USDT": 0.27,
  "APT/USDT:USDT": 4.7794,
  "ARB/USDT:USDT": 0.4466,
  "AR/USDT:USDT": 7.649,
  "ATOM/USDT:USDT": 4.72,
  "AVAX/USDT:USDT": 24.294,
  "BCH/USDT:USDT": 558.22,
  "BERA/USDT:USDT": 2.199,
  "BNB/USDT:USDT": 781.0,
  "CRV/USDT:USDT": 1.056,
  "DOGE/USDT:USDT": 0.23636,
  "DOT/USDT:USDT": 4.095,
  "EIGEN/USDT:USDT": 1.3633,
  "ENA/USDT:USDT": 0.5761,
  "ETC/USDT:USDT": 22.91,
  "ETH/USDT:USDT": 3742.25,
  "FARTCOIN/USDT:USDT": 1.3705,
  "FLOKI/USDT:USDT": 0.00013035,
  "FXS/USDT:USDT": 3.289,
  "GOAT/USDT:USDT": 0.12085,
  "GRASS/USDT:USDT": 0.9319,
  "HBAR/USDT:USDT": 0.2683,
  "HYPE/USDT:USDT": 44.35,
  "INJ/USDT:USDT": 14.4,
  "IP/USDT:USDT": 5.479,
  "JTO/USDT:USDT": 1.9717,
  "JUP/USDT:USDT": 0.5575,
  "KAITO/USDT:USDT": 1.3802,
  "LDO/USDT:USDT": 1.0843,
  "LINK/USDT:USDT": 18.251,
  "LTC/USDT:USDT": 113.52,
  "MEW/USDT:USDT": 0.003674,
  "MKR/USDT:USDT": 2248.6,
  "MOODENG/USDT:USDT": 0.2072,
  "MOVE/USDT:USDT": 0.1436,
  "NEAR/USDT:USDT": 2.859,
  "ONDO/USDT:USDT": 1.0473,
  "OP/USDT:USDT": 0.7195,
  "ORDI/USDT:USDT": 10.137,
  "PENDLE/USDT:USDT": 4.4509,
  "PENGU/USDT:USDT": 0.0435,
  "PEPE/USDT:USDT": 1.2584e-05,
  "PNUT/USDT:USDT": 0.2804,
  "POL/USDT:USDT": 0.23408,
  "POPCAT/USDT:USDT": 0.3826,
  "RENDER/USDT:USDT": 4.232,
  "RUNE/USDT:USDT": 1.486,
  "SEI/USDT:USDT": 0.3314,
  "SHIB/USDT:USDT": 1.4042e-05,
  "SOL/USDT:USDT": 187.49,
  "SPX/USDT:USDT": 2.0009,
  "STX/USDT:USDT": 0.8097,
  "SUI/USDT:USDT": 4.0426,
  "TAO/USDT:USDT": 426.9,
  "TIA/USDT:USDT": 1.935,
  "TRUMP/USDT:USDT": 0.1526,
  "TRX/USDT:USDT": 0.31719,
  "ZETA/USDT:USDT": 0.2188,
  "ZRO/USDT:USDT": 1.95
}