{
  "AAVE/USDT:USDT": 272.37,
  "ADA/USDT:USDT": 0.5574,
  "AI16Z/USDT:USDT": 0.1472,
  "AIXBT/USDT:USDT": 0.13272,
  "ALGO/USDT:USDT": 0.1788,
  "APT/USDT:USDT": 4.7954,
  "ARB/USDT:USDT": 0.3295,
  "AR/USDT:USDT": 5.169,
  "ATOM/USDT:USDT": 4.011,
  "AVAX/USDT:USDT": 17.91,
  "BCH/USDT:USDT": 491.82,
  "BERA/USDT:USDT": 1.704,
  "BNB/USDT:USDT": 648.32,
  "CRV/USDT:USDT": 0.5105,
  "DOGE/USDT:USDT": 0.16385,
  "DOT/USDT:USDT": 3.413,
  "EIGEN/USDT:USDT": 1.1,
  "ENA/USDT:USDT": 0.2648,
  "ETC/USDT:USDT": 16.44,
  "ETH/USDT:USDT": 2436.37,
  "FARTCOIN/USDT:USDT": 1.149,
  "FLOKI/USDT:USDT": 7.414e-05,
  "FXS/USDT:USDT": 1.981,
  "GOAT/USDT:USDT": 0.09677,
  "GRASS/USDT:USDT": 1.1662,
  "HBAR/USDT:USDT": 0.14749,
  "HYPE/USDT:USDT": 38.5,
  "INJ/USDT:USDT": 10.749,
  "IP/USDT:USDT": 3.071,
  "JTO/USDT:USDT": 2.255,
  "JUP/USDT:USDT": 0.4514,
  "KAITO/USDT:USDT": 1.5531,
  "LDO/USDT:USDT": 0.7221,
  "LINK/USDT:USDT": 13.295,
  "LTC/USDT:USDT": 86.65,
  "MEW/USDT:USDT": 0.002679,
  "MKR/USDT:USDT": 1956.3,
  "MOODENG/USDT:USDT": 0.14579,
  "MOVE/USDT:USDT": 0.1804,
  "NEAR/USDT:USDT": 2.125,
  "ONDO/USDT:USDT": 0.7624,
  "OP/USDT:USDT": 0.5531,
  "ORDI/USDT:USDT": 7.29,
  "PENDLE/USDT:USDT": 3.5714,
  "PENGU/USDT:USDT": 0.01395,
  "PEPE/USDT:USDT": 9.642e-06,
  "PNUT/USDT:USDT": 0.2196,
  "POL/USDT:USDT": 0.17761,
  "POPCAT/USDT:USDT": 0.3035,
  "RENDER/USDT:USDT": 3.224,
  "RUNE/USDT:USDT": 1.331,
  "SEI/USDT:USDT": 0.2999,
  "SHIB/USDT:USDT": 1.1539e-05,
  "SOL/USDT:USDT": 150.32,
  "SPX/USDT:USDT": 1.272,
  "STX/USDT:USDT": 0.6644,
  "SUI/USDT:USDT": 2.8251,
  "TAO/USDT:USDT": 342.0,
  "TIA/USDT:USDT": 1.441,
  "TRUMP/USDT:USDT": 0.1237,
  "TRX/USDT:USDT": 0.27596,
  "ZETA/USDT:USDT": 0.176,
  "ZRO/USDT:USDT": 1.838
}