{
  "AAVE/USDT:USDT": 325.41,
  "ADA/USDT:USDT": 0.7727,
  "AI16Z/USDT:USDT": 0.1938,
  "AIXBT/USDT:USDT": 0.17152,
  "ALGO/USDT:USDT": 0.2911,
  "APT/USDT:USDT": 5.2127,
  "ARB/USDT:USDT": 0.4502,
  "AR/USDT:USDT": 7.425,
  "ATOM/USDT:USDT": 4.762,
  "AVAX/USDT:USDT": 22.715,
  "BCH/USDT:USDT": 496.05,
  "BERA/USDT:USDT": 2.344,
  "BNB/USDT:USDT": 719.9,
  "CRV/USDT:USDT": 1.0167,
  "DOGE/USDT:USDT": 0.21232,
  "DOT/USDT:USDT": 4.201,
  "EIGEN/USDT:USDT": 1.4884,
  "ENA/USDT:USDT": 0.3775,
  "ETC/USDT:USDT": 20.065,
  "ETH/USDT:USDT": 3454.06,
  "FARTCOIN/USDT:USDT": 1.4436,
  "FLOKI/USDT:USDT": 0.00013264,
  "FXS/USDT:USDT": 2.876,
  "GOAT/USDT:USDT": 0.13344,
  "GRASS/USDT:USDT": 1.1513,
  "HBAR/USDT:USDT": 0.24112,
  "HYPE/USDT:USDT": 46.92,
  "INJ/USDT:USDT": 13.536,
  "IP/USDT:USDT": 4.366,
  "JTO/USDT:USDT": 1.9211,
  "JUP/USDT:USDT": 0.5446,
  "KAITO/USDT:USDT": 1.772,
  "LDO/USDT:USDT": 0.9472,
  "LINK/USDT:USDT": 16.984,
  "LTC/USDT:USDT": 98.36,
  "MEW/USDT:USDT": 0.004016,
  "MKR/USDT:USDT": 1906.7,
  "MOODENG/USDT:USDT": 0.20404,
  "MOVE/USDT:USDT": 0.1541,
  "NEAR/USDT:USDT": 2.751,
  "ONDO/USDT:USDT": 0.967,
  "OP/USDT:USDT": 0.7116,
  "ORDI/USDT:USDT": 10.231,
  "PENDLE/USDT:USDT": 4.2712,
  "PENGU/USDT:USDT": 0.03019,
  "PEPE/USDT:USDT": 1.3611e-05,
  "PNUT/USDT:USDT": 0.2997,
  "POL/USDT:USDT": 0.23297,
  "POPCAT/USDT:USDT": 0.4101,
  "RENDER/USDT:USDT": 4.056,
  "RUNE/USDT:USDT": 1.636,
  "SEI/USDT:USDT": 0.359,
  "SHIB/USDT:USDT": 1.44e-05,
  "SOL/USDT:USDT": 173.55,
  "SPX/USDT:USDT": 1.812,
  "STX/USDT:USDT": 0.8299,
  "SUI/USDT:USDT": 3.9954,
  "TAO/USDT:USDT": 430.5,
  "TIA/USDT:USDT": 1.984,
  "TRUMP/USDT:USDT": 0.1544,
  "TRX/USDT:USDT": 0.31144,
  "ZETA/USDT:USDT": 0.2213,
  "ZRO/USDT:USDT": 2.221
}