{
  "AAVE/USDT:USDT": 281.65,
  "ADA/USDT:USDT": 0.5797,
  "AI16Z/USDT:USDT": 0.1495,
  "AIXBT/USDT:USDT": 0.12989,
  "ALGO/USDT:USDT": 0.1743,
  "APT/USDT:USDT": 4.4413,
  "ARB/USDT:USDT": 0.3287,
  "AR/USDT:USDT": 5.062,
  "ATOM/USDT:USDT": 4.033,
  "AVAX/USDT:USDT": 17.928,
  "BCH/USDT:USDT": 490.46,
  "BERA/USDT:USDT": 1.648,
  "BNB/USDT:USDT": 658.54,
  "CRV/USDT:USDT": 0.5022,
  "DOGE/USDT:USDT": 0.16693,
  "DOT/USDT:USDT": 3.374,
  "EIGEN/USDT:USDT": 1.1216,
  "ENA/USDT:USDT": 0.2572,
  "ETC/USDT:USDT": 16.486,
  "ETH/USDT:USDT": 2530.76,
  "FARTCOIN/USDT:USDT": 1.1701,
  "FLOKI/USDT:USDT": 8.127e-05,
  "FXS/USDT:USDT": 1.953,
  "GOAT/USDT:USDT": 0.09658,
  "GRASS/USDT:USDT": 1.1836,
  "HBAR/USDT:USDT": 0.15868,
  "HYPE/USDT:USDT": 39.1,
  "INJ/USDT:USDT": 10.373,
  "IP/USDT:USDT": 3.087,
  "JTO/USDT:USDT": 1.826,
  "JUP/USDT:USDT": 0.435,
  "KAITO/USDT:USDT": 1.4703,
  "LDO/USDT:USDT": 0.7296,
  "LINK/USDT:USDT": 13.384,
  "LTC/USDT:USDT": 85.51,
  "MEW/USDT:USDT": 0.002682,
  "MKR/USDT:USDT": 1865.1,
  "MOODENG/USDT:USDT": 0.17918,
  "MOVE/USDT:USDT": 0.1503,
  "NEAR/USDT:USDT": 2.146,
  "ONDO/USDT:USDT": 0.7772,
  "OP/USDT:USDT": 0.5403,
  "ORDI/USDT:USDT": 7.477,
  "PENDLE/USDT:USDT": 3.3546,
  "PENGU/USDT:USDT": 0.01463,
  "PEPE/USDT:USDT": 9.944e-06,
  "PNUT/USDT:USDT": 0.2116,
  "POL/USDT:USDT": 0.1835,
  "POPCAT/USDT:USDT": 0.2897,
  "RENDER/USDT:USDT": 3.144,
  "RUNE/USDT:USDT": 1.314,
  "SEI/USDT:USDT": 0.2563,
  "SHIB/USDT:USDT": 1.1506e-05,
  "SOL/USDT:USDT": 149.79,
  "SPX/USDT:USDT": 1.2862,
  "STX/USDT:USDT": 0.6478,
  "SUI/USDT:USDT": 2.8608,
  "TAO/USDT:USDT": 320.8,
  "TIA/USDT:USDT": 1.575,
  "TRUMP/USDT:USDT": 0.1261,
  "TRX/USDT:USDT": 0.28613,
  "ZETA/USDT:USDT": 0.1751,
  "ZRO/USDT:USDT": 1.786
}