{
  "AAVE/USDT:USDT": 295.96,
  "ADA/USDT:USDT": 0.7057,
  "AI16Z/USDT:USDT": 0.1756,
  "AIXBT/USDT:USDT": 0.14397,
  "ALGO/USDT:USDT": 0.2176,
  "APT/USDT:USDT": 4.7654,
  "ARB/USDT:USDT": 0.3904,
  "AR/USDT:USDT": 6.155,
  "ATOM/USDT:USDT": 4.565,
  "AVAX/USDT:USDT": 20.609,
  "BCH/USDT:USDT": 505.65,
  "BERA/USDT:USDT": 1.916,
  "BNB/USDT:USDT": 685.62,
  "CRV/USDT:USDT": 0.6141,
  "DOGE/USDT:USDT": 0.1956,
  "DOT/USDT:USDT": 3.873,
  "EIGEN/USDT:USDT": 1.2903,
  "ENA/USDT:USDT": 0.3203,
  "ETC/USDT:USDT": 18.042,
  "ETH/USDT:USDT": 2926.56,
  "FARTCOIN/USDT:USDT": 1.221,
  "FLOKI/USDT:USDT": 9.399e-05,
  "FXS/USDT:USDT": 2.175,
  "GOAT/USDT:USDT": 0.12319,
  "GRASS/USDT:USDT": 1.1075,
  "HBAR/USDT:USDT": 0.19612,
  "HYPE/USDT:USDT": 45.61,
  "INJ/USDT:USDT": 12.339,
  "IP/USDT:USDT": 4.226,
  "JTO/USDT:USDT": 1.8853,
  "JUP/USDT:USDT": 0.4685,
  "KAITO/USDT:USDT": 1.5389,
  "LDO/USDT:USDT": 0.8085,
  "LINK/USDT:USDT": 14.942,
  "LTC/USDT:USDT": 91.74,
  "MEW/USDT:USDT": 0.003055,
  "MKR/USDT:USDT": 1831.4,
  "MOODENG/USDT:USDT": 0.1817,
  "MOVE/USDT:USDT": 0.1496,
  "NEAR/USDT:USDT": 2.459,
  "ONDO/USDT:USDT": 0.8675,
  "OP/USDT:USDT": 0.639,
  "ORDI/USDT:USDT": 9.143,
  "PENDLE/USDT:USDT": 3.7842,
  "PENGU/USDT:USDT": 0.02205,
  "PEPE/USDT:USDT": 1.2134e-05,
  "PNUT/USDT:USDT": 0.2698,
  "POL/USDT:USDT": 0.22731,
  "POPCAT/USDT:USDT": 0.36,
  "RENDER/USDT:USDT": 3.548,
  "RUNE/USDT:USDT": 1.473,
  "SEI/USDT:USDT": 0.3215,
  "SHIB/USDT:USDT": 1.3118e-05,
  "SOL/USDT:USDT": 158.9,
  "SPX/USDT:USDT": 1.5256,
  "STX/USDT:USDT": 0.732,
  "SUI/USDT:USDT": 3.3528,
  "TAO/USDT:USDT": 379.7,
  "TIA/USDT:USDT": 1.852,
  "TRUMP/USDT:USDT": 0.1399,
  "TRX/USDT:USDT": 0.30001,
  "ZETA/USDT:USDT": 0.2042,
  "ZRO/USDT:USDT": 2.032
}