{
  "AAVE/USDT:USDT": 286.99,
  "ADA/USDT:USDT": 0.5876,
  "AI16Z/USDT:USDT": 0.1577,
  "AIXBT/USDT:USDT": 0.13416,
  "ALGO/USDT:USDT": 0.1777,
  "APT/USDT:USDT": 4.4972,
  "ARB/USDT:USDT": 0.3353,
  "AR/USDT:USDT": 5.19,
  "ATOM/USDT:USDT": 4.094,
  "AVAX/USDT:USDT": 18.341,
  "BCH/USDT:USDT": 494.99,
  "BERA/USDT:USDT": 1.696,
  "BNB/USDT:USDT": 662.52,
  "CRV/USDT:USDT": 0.5072,
  "DOGE/USDT:USDT": 0.17175,
  "DOT/USDT:USDT": 3.415,
  "EIGEN/USDT:USDT": 1.1612,
  "ENA/USDT:USDT": 0.2644,
  "ETC/USDT:USDT": 16.742,
  "ETH/USDT:USDT": 2585.11,
  "FARTCOIN/USDT:USDT": 1.1966,
  "FLOKI/USDT:USDT": 8.529e-05,
  "FXS/USDT:USDT": 1.979,
  "GOAT/USDT:USDT": 0.10067,
  "GRASS/USDT:USDT": 1.127,
  "HBAR/USDT:USDT": 0.15977,
  "HYPE/USDT:USDT": 39.75,
  "INJ/USDT:USDT": 10.77,
  "IP/USDT:USDT": 3.048,
  "JTO/USDT:USDT": 1.9909,
  "JUP/USDT:USDT": 0.4519,
  "KAITO/USDT:USDT": 1.5572,
  "LDO/USDT:USDT": 0.7466,
  "LINK/USDT:USDT": 13.561,
  "LTC/USDT:USDT": 87.87,
  "MEW/USDT:USDT": 0.002788,
  "MKR/USDT:USDT": 1894.1,
  "MOODENG/USDT:USDT": 0.19182,
  "MOVE/USDT:USDT": 0.1559,
  "NEAR/USDT:USDT": 2.197,
  "ONDO/USDT:USDT": 0.8005,
  "OP/USDT:USDT": 0.5484,
  "ORDI/USDT:USDT": 7.679,
  "PENDLE/USDT:USDT": 3.4338,
  "PENGU/USDT:USDT": 0.01599,
  "PEPE/USDT:USDT": 1.0142e-05,
  "PNUT/USDT:USDT": 0.2282,
  "POL/USDT:USDT": 0.1847,
  "POPCAT/USDT:USDT": 0.3077,
  "RENDER/USDT:USDT": 3.247,
  "RUNE/USDT:USDT": 1.349,
  "SEI/USDT:USDT": 0.2656,
  "SHIB/USDT:USDT": 1.1855e-05,
  "SOL/USDT:USDT": 152.14,
  "SPX/USDT:USDT": 1.3259,
  "STX/USDT:USDT": 0.6626,
  "SUI/USDT:USDT": 2.9349,
  "TAO/USDT:USDT": 329.2,
  "TIA/USDT:USDT": 1.6,
  "TRUMP/USDT:USDT": 0.1295,
  "TRX/USDT:USDT": 0.28574,
  "ZETA/USDT:USDT": 0.1788,
  "ZRO/USDT:USDT": 1.832
}