{
  "AAVE/USDT:USDT": 300.63,
  "ADA/USDT:USDT": 0.5973,
  "AI16Z/USDT:USDT": 0.1534,
  "AIXBT/USDT:USDT": 0.12669,
  "ALGO/USDT:USDT": 0.1829,
  "APT/USDT:USDT": 4.5013,
  "ARB/USDT:USDT": 0.3401,
  "AR/USDT:USDT": 5.296,
  "ATOM/USDT:USDT": 4.167,
  "AVAX/USDT:USDT": 18.408,
  "BCH/USDT:USDT": 507.31,
  "BERA/USDT:USDT": 1.698,
  "BNB/USDT:USDT": 661.74,
  "CRV/USDT:USDT": 0.5474,
  "DOGE/USDT:USDT": 0.17163,
  "DOT/USDT:USDT": 3.478,
  "EIGEN/USDT:USDT": 1.1627,
  "ENA/USDT:USDT": 0.2679,
  "ETC/USDT:USDT": 17.052,
  "ETH/USDT:USDT": 2621.41,
  "FARTCOIN/USDT:USDT": 1.0535,
  "FLOKI/USDT:USDT": 9.258e-05,
  "FXS/USDT:USDT": 2.019,
  "GOAT/USDT:USDT": 0.09829,
  "GRASS/USDT:USDT": 1.1807,
  "HBAR/USDT:USDT": 0.16337,
  "HYPE/USDT:USDT": 39.37,
  "INJ/USDT:USDT": 10.526,
  "IP/USDT:USDT": 3.014,
  "JTO/USDT:USDT": 1.8695,
  "JUP/USDT:USDT": 0.4379,
  "KAITO/USDT:USDT": 1.4673,
  "LDO/USDT:USDT": 0.7294,
  "LINK/USDT:USDT": 14.151,
  "LTC/USDT:USDT": 88.03,
  "MEW/USDT:USDT": 0.002774,
  "MKR/USDT:USDT": 1918.6,
  "MOODENG/USDT:USDT": 0.17761,
  "MOVE/USDT:USDT": 0.1464,
  "NEAR/USDT:USDT": 2.255,
  "ONDO/USDT:USDT": 0.8042,
  "OP/USDT:USDT": 0.5509,
  "ORDI/USDT:USDT": 7.73,
  "PENDLE/USDT:USDT": 3.465,
  "PENGU/USDT:USDT": 0.01477,
  "PEPE/USDT:USDT": 1.0267e-05,
  "PNUT/USDT:USDT": 0.2239,
  "POL/USDT:USDT": 0.20295,
  "POPCAT/USDT:USDT": 0.2948,
  "RENDER/USDT:USDT": 3.221,
  "RUNE/USDT:USDT": 1.364,
  "SEI/USDT:USDT": 0.2625,
  "SHIB/USDT:USDT": 1.1949e-05,
  "SOL/USDT:USDT": 152.73,
  "SPX/USDT:USDT": 1.4422,
  "TAO/USDT:USDT": 326.4,
  "TIA/USDT:USDT": 1.633,
  "TRUMP/USDT:USDT": 0.1275,
  "TRX/USDT:USDT": 0.28668,
  "ZETA/USDT:USDT": 0.1821,
  "ZRO/USDT:USDT": 1.823
}