{
  "AAVE/USDT:USDT": 260.69,
  "ADA/USDT:USDT": 0.7346,
  "AI16Z/USDT:USDT": 0.1281,
  "AIXBT/USDT:USDT": 0.12273,
  "ALGO/USDT:USDT": 0.2445,
  "APT/USDT:USDT": 4.3494,
  "ARB/USDT:USDT": 0.3953,
  "AR/USDT:USDT": 6.929,
  "ATOM/USDT:USDT": 4.215,
  "AVAX/USDT:USDT": 22.327,
  "BCH/USDT:USDT": 561.82,
  "BERA/USDT:USDT": 1.859,
  "BNB/USDT:USDT": 784.12,
  "CRV/USDT:USDT": 0.9435,
  "DOGE/USDT:USDT": 0.20888,
  "DOT/USDT:USDT": 3.696,
  "EIGEN/USDT:USDT": 1.1511,
  "ENA/USDT:USDT": 0.601,
  "ETC/USDT:USDT": 20.501,
  "ETH/USDT:USDT": 3707.39,
  "FARTCOIN/USDT:USDT": 0.9854,
  "FLOKI/USDT:USDT": 0.00010996,
  "FXS/USDT:USDT": 3.026,
  "GOAT/USDT:USDT": 0.09771,
  "GRASS/USDT:USDT": 0.7067,
  "HBAR/USDT:USDT": 0.25297,
  "HYPE/USDT:USDT": 41.31,
  "INJ/USDT:USDT": 13.231,
  "IP/USDT:USDT": 6.003,
  "JTO/USDT:USDT": 1.6777,
  "JUP/USDT:USDT": 0.4832,
  "KAITO/USDT:USDT": 1.16,
  "LDO/USDT:USDT": 0.9501,
  "LINK/USDT:USDT": 16.886,
  "LTC/USDT:USDT": 106.3,
  "MEW/USDT:USDT": 0.003102,
  "MKR/USDT:USDT": 1978.5,
  "MOODENG/USDT:USDT": 0.16573,
  "MOVE/USDT:USDT": 0.1331,
  "NEAR/USDT:USDT": 2.531,
  "ONDO/USDT:USDT": 0.9179,
  "OP/USDT:USDT": 0.6678,
  "ORDI/USDT:USDT": 9.124,
  "PENDLE/USDT:USDT": 4.0342,
  "PENGU/USDT:USDT": 0.03401,
  "PEPE/USDT:USDT": 1.0738e-05,
  "PNUT/USDT:USDT": 0.2337,
  "POL/USDT:USDT": 0.20288,
  "POPCAT/USDT:USDT": 0.3088,
  "RENDER/USDT:USDT": 3.7,
  "RUNE/USDT:USDT": 1.322,
  "SEI/USDT:USDT": 0.2924,
  "SHIB/USDT:USDT": 1.2407e-05,
  "SOL/USDT:USDT": 171.07,
  "SPX/USDT:USDT": 1.6598,
  "STX/USDT:USDT": 0.7074,
  "SUI/USDT:USDT": 3.5992,
  "TAO/USDT:USDT": 354.8,
  "TIA/USDT:USDT": 1.691,
  "TRUMP/USDT:USDT": 0.1486,
  "TRX/USDT:USDT": 0.3265,
  "ZETA/USDT:USDT": 0.1876,
  "ZRO/USDT:USDT": 1.716
}