{
  "AAVE/USDT:USDT": 303.9,
  "ADA/USDT:USDT": 0.8095,
  "AI16Z/USDT:USDT": 0.1402,
  "AIXBT/USDT:USDT": 0.13268,
  "ALGO/USDT:USDT": 0.2718,
  "APT/USDT:USDT": 4.8004,
  "ARB/USDT:USDT": 0.462,
  "AR/USDT:USDT": 7.837,
  "ATOM/USDT:USDT": 4.721,
  "AVAX/USDT:USDT": 24.205,
  "BCH/USDT:USDT": 569.0,
  "BERA/USDT:USDT": 2.096,
  "BNB/USDT:USDT": 803.87,
  "CRV/USDT:USDT": 0.9917,
  "DOGE/USDT:USDT": 0.24052,
  "DOT/USDT:USDT": 4.097,
  "EIGEN/USDT:USDT": 1.4116,
  "ENA/USDT:USDT": 0.746,
  "ETC/USDT:USDT": 23.184,
  "ETH/USDT:USDT": 4203.52,
  "FARTCOIN/USDT:USDT": 1.079,
  "FLOKI/USDT:USDT": 0.00011907,
  "FXS/USDT:USDT": 3.166,
  "GOAT/USDT:USDT": 0.10616,
  "GRASS/USDT:USDT": 0.8243,
  "HBAR/USDT:USDT": 0.26293,
  "HYPE/USDT:USDT": 43.77,
  "INJ/USDT:USDT": 14.546,
  "IP/USDT:USDT": 6.399,
  "JTO/USDT:USDT": 1.8641,
  "JUP/USDT:USDT": 0.5215,
  "KAITO/USDT:USDT": 1.2345,
  "LDO/USDT:USDT": 1.1917,
  "LINK/USDT:USDT": 21.178,
  "LTC/USDT:USDT": 121.5,
  "MEW/USDT:USDT": 0.003362,
  "MKR/USDT:USDT": 2059.0,
  "MOODENG/USDT:USDT": 0.17819,
  "MOVE/USDT:USDT": 0.1418,
  "NEAR/USDT:USDT": 2.799,
  "ONDO/USDT:USDT": 1.0405,
  "OP/USDT:USDT": 0.7938,
  "ORDI/USDT:USDT": 10.434,
  "PENDLE/USDT:USDT": 5.5907,
  "PENGU/USDT:USDT": 0.03773,
  "PEPE/USDT:USDT": 1.2223e-05,
  "PNUT/USDT:USDT": 0.2567,
  "POL/USDT:USDT": 0.2472,
  "POPCAT/USDT:USDT": 0.3347,
  "RENDER/USDT:USDT": 3.964,
  "RUNE/USDT:USDT": 1.428,
  "SEI/USDT:USDT": 0.3303,
  "SHIB/USDT:USDT": 1.3758e-05,
  "SOL/USDT:USDT": 179.59,
  "SPX/USDT:USDT": 1.9087,
  "STX/USDT:USDT": 0.7509,
  "SUI/USDT:USDT": 3.9171,
  "TAO/USDT:USDT": 386.3,
  "TIA/USDT:USDT": 1.83,
  "TRUMP/USDT:USDT": 0.1568,
  "TRX/USDT:USDT": 0.33545,
  "ZETA/USDT:USDT": 0.2065,
  "ZRO/USDT:USDT": 1.927
}