{
  "AAVE/USDT:USDT": 322.62,
  "ADA/USDT:USDT": 0.7745,
  "AI16Z/USDT:USDT": 0.1996,
  "AIXBT/USDT:USDT": 0.18059,
  "ALGO/USDT:USDT": 0.2926,
  "APT/USDT:USDT": 5.2046,
  "ARB/USDT:USDT": 0.4489,
  "AR/USDT:USDT": 7.398,
  "ATOM/USDT:USDT": 4.756,
  "AVAX/USDT:USDT": 22.656,
  "BCH/USDT:USDT": 494.34,
  "BERA/USDT:USDT": 2.336,
  "BNB/USDT:USDT": 716.84,
  "CRV/USDT:USDT": 0.9991,
  "DOGE/USDT:USDT": 0.21217,
  "DOT/USDT:USDT": 4.194,
  "EIGEN/USDT:USDT": 1.512,
  "ENA/USDT:USDT": 0.3768,
  "ETC/USDT:USDT": 19.926,
  "ETH/USDT:USDT": 3432.68,
  "FARTCOIN/USDT:USDT": 1.4505,
  "FLOKI/USDT:USDT": 0.00013319,
  "FXS/USDT:USDT": 3.021,
  "GOAT/USDT:USDT": 0.13517,
  "GRASS/USDT:USDT": 1.1711,
  "HBAR/USDT:USDT": 0.24242,
  "HYPE/USDT:USDT": 46.15,
  "INJ/USDT:USDT": 13.571,
  "IP/USDT:USDT": 4.347,
  "JTO/USDT:USDT": 1.9276,
  "JUP/USDT:USDT": 0.5431,
  "KAITO/USDT:USDT": 1.7524,
  "LDO/USDT:USDT": 0.9432,
  "LINK/USDT:USDT": 17.002,
  "LTC/USDT:USDT": 98.35,
  "MEW/USDT:USDT": 0.003947,
  "MKR/USDT:USDT": 1884.8,
  "MOODENG/USDT:USDT": 0.20303,
  "MOVE/USDT:USDT": 0.1536,
  "NEAR/USDT:USDT": 2.757,
  "ONDO/USDT:USDT": 0.9606,
  "OP/USDT:USDT": 0.7137,
  "ORDI/USDT:USDT": 10.286,
  "PENDLE/USDT:USDT": 4.2186,
  "PENGU/USDT:USDT": 0.03118,
  "PEPE/USDT:USDT": 1.358e-05,
  "PNUT/USDT:USDT": 0.3008,
  "POL/USDT:USDT": 0.23244,
  "POPCAT/USDT:USDT": 0.414,
  "RENDER/USDT:USDT": 4.045,
  "RUNE/USDT:USDT": 1.631,
  "SEI/USDT:USDT": 0.3563,
  "SHIB/USDT:USDT": 1.4358e-05,
  "SOL/USDT:USDT": 173.08,
  "SPX/USDT:USDT": 1.838,
  "STX/USDT:USDT": 0.8302,
  "SUI/USDT:USDT": 3.9957,
  "TAO/USDT:USDT": 426.7,
  "TIA/USDT:USDT": 1.969,
  "TRUMP/USDT:USDT": 0.1563,
  "TRX/USDT:USDT": 0.31096,
  "ZETA/USDT:USDT": 0.2213,
  "ZRO/USDT:USDT": 2.241
}