{
  "AAVE/USDT:USDT": 278.92,
  "ADA/USDT:USDT": 0.5752,
  "AI16Z/USDT:USDT": 0.1472,
  "AIXBT/USDT:USDT": 0.12555,
  "ALGO/USDT:USDT": 0.1738,
  "APT/USDT:USDT": 4.4313,
  "ARB/USDT:USDT": 0.3263,
  "AR/USDT:USDT": 5.011,
  "ATOM/USDT:USDT": 4.02,
  "AVAX/USDT:USDT": 17.848,
  "BCH/USDT:USDT": 492.89,
  "BERA/USDT:USDT": 1.631,
  "BNB/USDT:USDT": 659.01,
  "CRV/USDT:USDT": 0.5,
  "DOGE/USDT:USDT": 0.16668,
  "DOT/USDT:USDT": 3.35,
  "EIGEN/USDT:USDT": 1.114,
  "ENA/USDT:USDT": 0.2546,
  "ETC/USDT:USDT": 16.42,
  "ETH/USDT:USDT": 2531.2,
  "FARTCOIN/USDT:USDT": 1.0806,
  "FLOKI/USDT:USDT": 8.063e-05,
  "FXS/USDT:USDT": 1.939,
  "GOAT/USDT:USDT": 0.09553,
  "GRASS/USDT:USDT": 1.1693,
  "HBAR/USDT:USDT": 0.15684,
  "HYPE/USDT:USDT": 38.39,
  "INJ/USDT:USDT": 10.329,
  "IP/USDT:USDT": 3.135,
  "JTO/USDT:USDT": 1.8357,
  "JUP/USDT:USDT": 0.4298,
  "KAITO/USDT:USDT": 1.4656,
  "LDO/USDT:USDT": 0.7244,
  "LINK/USDT:USDT": 13.315,
  "LTC/USDT:USDT": 85.76,
  "MEW/USDT:USDT": 0.002642,
  "MKR/USDT:USDT": 1865.2,
  "MOODENG/USDT:USDT": 0.17615,
  "MOVE/USDT:USDT": 0.1487,
  "NEAR/USDT:USDT": 2.139,
  "ONDO/USDT:USDT": 0.7711,
  "OP/USDT:USDT": 0.5386,
  "ORDI/USDT:USDT": 7.413,
  "PENDLE/USDT:USDT": 3.3509,
  "PENGU/USDT:USDT": 0.01438,
  "PEPE/USDT:USDT": 9.791e-06,
  "PNUT/USDT:USDT": 0.2114,
  "POL/USDT:USDT": 0.18352,
  "POPCAT/USDT:USDT": 0.2792,
  "RENDER/USDT:USDT": 3.127,
  "RUNE/USDT:USDT": 1.311,
  "SEI/USDT:USDT": 0.2551,
  "SHIB/USDT:USDT": 1.1512e-05,
  "SOL/USDT:USDT": 148.23,
  "SPX/USDT:USDT": 1.2275,
  "STX/USDT:USDT": 0.6409,
  "SUI/USDT:USDT": 2.8399,
  "TAO/USDT:USDT": 318.4,
  "TIA/USDT:USDT": 1.559,
  "TRUMP/USDT:USDT": 0.1261,
  "TRX/USDT:USDT": 0.28589,
  "ZETA/USDT:USDT": 0.1738,
  "ZRO/USDT:USDT": 1.776
}