{
  "AAVE/USDT:USDT": 227.52,
  "ADA/USDT:USDT": 0.5394,
  "AI16Z/USDT:USDT": 0.1327,
  "AIXBT/USDT:USDT": 0.11503,
  "ALGO/USDT:USDT": 0.1559,
  "APT/USDT:USDT": 3.9197,
  "ARB/USDT:USDT": 0.262,
  "AR/USDT:USDT": 4.652,
  "ATOM/USDT:USDT": 3.69,
  "AVAX/USDT:USDT": 16.371,
  "BCH/USDT:USDT": 459.0,
  "BERA/USDT:USDT": 1.578,
  "BNB/USDT:USDT": 621.52,
  "CRV/USDT:USDT": 0.5255,
  "DOGE/USDT:USDT": 0.15236,
  "DOT/USDT:USDT": 3.221,
  "EIGEN/USDT:USDT": 0.9922,
  "ENA/USDT:USDT": 0.2363,
  "ETC/USDT:USDT": 15.191,
  "ETH/USDT:USDT": 2229.0,
  "FARTCOIN/USDT:USDT": 0.8258,
  "FLOKI/USDT:USDT": 6.295e-05,
  "FXS/USDT:USDT": 2.179,
  "GOAT/USDT:USDT": 0.08236,
  "GRASS/USDT:USDT": 1.1102,
  "HBAR/USDT:USDT": 0.13187,
  "HYPE/USDT:USDT": 32.5,
  "INJ/USDT:USDT": 9.422,
  "IP/USDT:USDT": 2.726,
  "JTO/USDT:USDT": 2.002,
  "JUP/USDT:USDT": 0.3412,
  "KAITO/USDT:USDT": 1.2365,
  "LDO/USDT:USDT": 0.6493,
  "LINK/USDT:USDT": 11.655,
  "LTC/USDT:USDT": 79.81,
  "MEW/USDT:USDT": 0.002301,
  "MKR/USDT:USDT": 1689.7,
  "MOODENG/USDT:USDT": 0.12391,
  "MOVE/USDT:USDT": 0.1171,
  "NEAR/USDT:USDT": 1.864,
  "ONDO/USDT:USDT": 0.6565,
  "OP/USDT:USDT": 0.482,
  "ORDI/USDT:USDT": 6.432,
  "PENDLE/USDT:USDT": 3.3216,
  "PENGU/USDT:USDT": 0.00801,
  "PEPE/USDT:USDT": 8.738e-06,
  "PNUT/USDT:USDT": 0.188,
  "POL/USDT:USDT": 0.1699,
  "POPCAT/USDT:USDT": 0.2441,
  "RENDER/USDT:USDT": 2.77,
  "RUNE/USDT:USDT": 1.23,
  "SEI/USDT:USDT": 0.194,
  "SHIB/USDT:USDT": 1.0497e-05,
  "SOL/USDT:USDT": 130.35,
  "SPX/USDT:USDT": 0.948,
  "STX/USDT:USDT": 0.5497,
  "SUI/USDT:USDT": 2.4689,
  "TAO/USDT:USDT": 298.7,
  "TIA/USDT:USDT": 1.376,
  "TRUMP/USDT:USDT": 0.1211,
  "TRX/USDT:USDT": 0.26906,
  "ZETA/USDT:USDT": 0.1607,
  "ZRO/USDT:USDT": 1.556
}