{
  "AAVE/USDT:USDT": 246.56,
  "ADA/USDT:USDT": 0.5847,
  "AI16Z/USDT:USDT": 0.1539,
  "AIXBT/USDT:USDT": 0.13375,
  "ALGO/USDT:USDT": 0.1676,
  "APT/USDT:USDT": 4.3104,
  "ARB/USDT:USDT": 0.2902,
  "AR/USDT:USDT": 5.116,
  "ATOM/USDT:USDT": 3.942,
  "AVAX/USDT:USDT": 17.483,
  "BCH/USDT:USDT": 466.45,
  "BERA/USDT:USDT": 1.797,
  "BNB/USDT:USDT": 643.84,
  "CRV/USDT:USDT": 0.5764,
  "DOGE/USDT:USDT": 0.16317,
  "DOT/USDT:USDT": 3.449,
  "EIGEN/USDT:USDT": 1.121,
  "ENA/USDT:USDT": 0.2696,
  "ETC/USDT:USDT": 16.168,
  "ETH/USDT:USDT": 2423.87,
  "FARTCOIN/USDT:USDT": 0.9297,
  "FLOKI/USDT:USDT": 7.169e-05,
  "FXS/USDT:USDT": 2.28,
  "GOAT/USDT:USDT": 0.09514,
  "GRASS/USDT:USDT": 1.2259,
  "HBAR/USDT:USDT": 0.14493,
  "HYPE/USDT:USDT": 34.39,
  "INJ/USDT:USDT": 11.139,
  "IP/USDT:USDT": 2.647,
  "JTO/USDT:USDT": 2.098,
  "JUP/USDT:USDT": 0.3829,
  "KAITO/USDT:USDT": 1.3717,
  "LDO/USDT:USDT": 0.739,
  "LINK/USDT:USDT": 12.623,
  "LTC/USDT:USDT": 83.46,
  "MEW/USDT:USDT": 0.002583,
  "MKR/USDT:USDT": 1846.3,
  "MOODENG/USDT:USDT": 0.14295,
  "MOVE/USDT:USDT": 0.1266,
  "NEAR/USDT:USDT": 2.088,
  "ONDO/USDT:USDT": 0.7381,
  "OP/USDT:USDT": 0.5499,
  "ORDI/USDT:USDT": 7.303,
  "PENDLE/USDT:USDT": 3.6656,
  "PENGU/USDT:USDT": 0.00905,
  "PEPE/USDT:USDT": 1e-05,
  "PNUT/USDT:USDT": 0.2244,
  "POL/USDT:USDT": 0.18441,
  "POPCAT/USDT:USDT": 0.283,
  "RENDER/USDT:USDT": 3.065,
  "RUNE/USDT:USDT": 1.346,
  "SEI/USDT:USDT": 0.2132,
  "SHIB/USDT:USDT": 1.137e-05,
  "SOL/USDT:USDT": 139.74,
  "SPX/USDT:USDT": 1.0857,
  "STX/USDT:USDT": 0.6108,
  "SUI/USDT:USDT": 2.7159,
  "TAO/USDT:USDT": 339.1,
  "TIA/USDT:USDT": 1.595,
  "TRUMP/USDT:USDT": 0.1338,
  "TRX/USDT:USDT": 0.27235,
  "ZETA/USDT:USDT": 0.1743,
  "ZRO/USDT:USDT": 1.722
}