{
  "AAVE/USDT:USDT": 274.18,
  "ADA/USDT:USDT": 0.6272,
  "AI16Z/USDT:USDT": 0.1778,
  "AIXBT/USDT:USDT": 0.1638,
  "ALGO/USDT:USDT": 0.1741,
  "APT/USDT:USDT": 4.5917,
  "ARB/USDT:USDT": 0.3147,
  "AR/USDT:USDT": 5.715,
  "ATOM/USDT:USDT": 4.099,
  "AVAX/USDT:USDT": 19.015,
  "BCH/USDT:USDT": 474.74,
  "BERA/USDT:USDT": 2.0,
  "BNB/USDT:USDT": 657.93,
  "CRV/USDT:USDT": 0.5913,
  "DOGE/USDT:USDT": 0.17295,
  "DOT/USDT:USDT": 3.796,
  "EIGEN/USDT:USDT": 1.1574,
  "ENA/USDT:USDT": 0.2906,
  "ETC/USDT:USDT": 16.895,
  "ETH/USDT:USDT": 2574.65,
  "FARTCOIN/USDT:USDT": 1.1622,
  "FLOKI/USDT:USDT": 7.654e-05,
  "FXS/USDT:USDT": 2.528,
  "GOAT/USDT:USDT": 0.10154,
  "GRASS/USDT:USDT": 1.4838,
  "HBAR/USDT:USDT": 0.15455,
  "HYPE/USDT:USDT": 41.77,
  "INJ/USDT:USDT": 11.405,
  "IP/USDT:USDT": 3.466,
  "JTO/USDT:USDT": 2.2673,
  "JUP/USDT:USDT": 0.4156,
  "KAITO/USDT:USDT": 1.4441,
  "LDO/USDT:USDT": 0.8092,
  "LINK/USDT:USDT": 13.423,
  "LTC/USDT:USDT": 86.01,
  "MEW/USDT:USDT": 0.002793,
  "MKR/USDT:USDT": 2175.9,
  "MOODENG/USDT:USDT": 0.15813,
  "MOVE/USDT:USDT": 0.1386,
  "NEAR/USDT:USDT": 2.218,
  "ONDO/USDT:USDT": 0.7674,
  "OP/USDT:USDT": 0.5745,
  "ORDI/USDT:USDT": 7.88,
  "PENDLE/USDT:USDT": 3.9098,
  "PENGU/USDT:USDT": 0.00989,
  "PEPE/USDT:USDT": 1.0518e-05,
  "PNUT/USDT:USDT": 0.2296,
  "POL/USDT:USDT": 0.19837,
  "POPCAT/USDT:USDT": 0.3104,
  "RENDER/USDT:USDT": 3.337,
  "RUNE/USDT:USDT": 1.49,
  "SEI/USDT:USDT": 0.1684,
  "SHIB/USDT:USDT": 1.1827e-05,
  "SOL/USDT:USDT": 151.87,
  "SPX/USDT:USDT": 1.4441,
  "STX/USDT:USDT": 0.6352,
  "SUI/USDT:USDT": 2.9685,
  "TAO/USDT:USDT": 356.1,
  "TIA/USDT:USDT": 1.681,
  "TRUMP/USDT:USDT": 0.1533,
  "TRX/USDT:USDT": 0.27702,
  "ZETA/USDT:USDT": 0.1917,
  "ZRO/USDT:USDT": 1.877
}