{
  "AAVE/USDT:USDT": 259.59,
  "ADA/USDT:USDT": 0.5789,
  "AI16Z/USDT:USDT": 0.1614,
  "AIXBT/USDT:USDT": 0.14324,
  "ALGO/USDT:USDT": 0.1782,
  "APT/USDT:USDT": 4.3085,
  "ARB/USDT:USDT": 0.3114,
  "AR/USDT:USDT": 5.202,
  "ATOM/USDT:USDT": 4.014,
  "AVAX/USDT:USDT": 18.026,
  "BCH/USDT:USDT": 457.86,
  "BERA/USDT:USDT": 1.748,
  "BNB/USDT:USDT": 638.36,
  "CRV/USDT:USDT": 0.5786,
  "DOGE/USDT:USDT": 0.16326,
  "DOT/USDT:USDT": 3.4,
  "EIGEN/USDT:USDT": 1.1452,
  "ENA/USDT:USDT": 0.2674,
  "ETC/USDT:USDT": 16.253,
  "ETH/USDT:USDT": 2400.29,
  "FARTCOIN/USDT:USDT": 1.0228,
  "FLOKI/USDT:USDT": 7.319e-05,
  "FXS/USDT:USDT": 2.342,
  "GOAT/USDT:USDT": 0.09926,
  "GRASS/USDT:USDT": 1.1793,
  "HBAR/USDT:USDT": 0.15089,
  "HYPE/USDT:USDT": 36.8,
  "INJ/USDT:USDT": 11.494,
  "IP/USDT:USDT": 3.127,
  "JTO/USDT:USDT": 2.1248,
  "JUP/USDT:USDT": 0.4126,
  "KAITO/USDT:USDT": 1.416,
  "LDO/USDT:USDT": 0.7074,
  "LINK/USDT:USDT": 13.038,
  "LTC/USDT:USDT": 84.41,
  "MEW/USDT:USDT": 0.002664,
  "MKR/USDT:USDT": 1973.8,
  "MOODENG/USDT:USDT": 0.15212,
  "MOVE/USDT:USDT": 0.1582,
  "NEAR/USDT:USDT": 2.171,
  "ONDO/USDT:USDT": 0.762,
  "OP/USDT:USDT": 0.5498,
  "ORDI/USDT:USDT": 7.417,
  "PENDLE/USDT:USDT": 3.5684,
  "PENGU/USDT:USDT": 0.00985,
  "PEPE/USDT:USDT": 9.938e-06,
  "PNUT/USDT:USDT": 0.2223,
  "POL/USDT:USDT": 0.17951,
  "POPCAT/USDT:USDT": 0.3026,
  "RENDER/USDT:USDT": 3.23,
  "RUNE/USDT:USDT": 1.359,
  "SEI/USDT:USDT": 0.2823,
  "SHIB/USDT:USDT": 1.1676e-05,
  "SOL/USDT:USDT": 143.99,
  "SPX/USDT:USDT": 1.223,
  "STX/USDT:USDT": 0.6401,
  "SUI/USDT:USDT": 2.7895,
  "TAO/USDT:USDT": 352.1,
  "TIA/USDT:USDT": 1.582,
  "TRUMP/USDT:USDT": 0.1282,
  "TRX/USDT:USDT": 0.27165,
  "ZETA/USDT:USDT": 0.1803,
  "ZRO/USDT:USDT": 1.824
}