{
  "AAVE/USDT:USDT": 260.51,
  "ADA/USDT:USDT": 0.5604,
  "AI16Z/USDT:USDT": 0.1427,
  "AIXBT/USDT:USDT": 0.13291,
  "ALGO/USDT:USDT": 0.1771,
  "APT/USDT:USDT": 4.7709,
  "ARB/USDT:USDT": 0.3068,
  "AR/USDT:USDT": 5.159,
  "ATOM/USDT:USDT": 3.994,
  "AVAX/USDT:USDT": 17.895,
  "BCH/USDT:USDT": 491.62,
  "BERA/USDT:USDT": 1.712,
  "BNB/USDT:USDT": 649.26,
  "CRV/USDT:USDT": 0.5129,
  "DOGE/USDT:USDT": 0.1637,
  "DOT/USDT:USDT": 3.396,
  "EIGEN/USDT:USDT": 1.0789,
  "ENA/USDT:USDT": 0.2623,
  "ETC/USDT:USDT": 16.33,
  "ETH/USDT:USDT": 2432.72,
  "FARTCOIN/USDT:USDT": 1.0828,
  "FLOKI/USDT:USDT": 7.38e-05,
  "FXS/USDT:USDT": 1.994,
  "GOAT/USDT:USDT": 0.09649,
  "GRASS/USDT:USDT": 1.1643,
  "HBAR/USDT:USDT": 0.14728,
  "HYPE/USDT:USDT": 37.86,
  "INJ/USDT:USDT": 10.863,
  "IP/USDT:USDT": 3.015,
  "JTO/USDT:USDT": 2.2461,
  "JUP/USDT:USDT": 0.4422,
  "KAITO/USDT:USDT": 1.564,
  "LDO/USDT:USDT": 0.7183,
  "LINK/USDT:USDT": 13.34,
  "LTC/USDT:USDT": 86.68,
  "MEW/USDT:USDT": 0.002655,
  "MKR/USDT:USDT": 1940.7,
  "MOODENG/USDT:USDT": 0.14566,
  "MOVE/USDT:USDT": 0.1732,
  "NEAR/USDT:USDT": 2.137,
  "ONDO/USDT:USDT": 0.7612,
  "OP/USDT:USDT": 0.5531,
  "ORDI/USDT:USDT": 7.206,
  "PENDLE/USDT:USDT": 3.5281,
  "PENGU/USDT:USDT": 0.01331,
  "PEPE/USDT:USDT": 9.436e-06,
  "PNUT/USDT:USDT": 0.2163,
  "POL/USDT:USDT": 0.17739,
  "POPCAT/USDT:USDT": 0.2974,
  "RENDER/USDT:USDT": 3.227,
  "RUNE/USDT:USDT": 1.346,
  "SEI/USDT:USDT": 0.3,
  "SHIB/USDT:USDT": 1.1522e-05,
  "SOL/USDT:USDT": 149.56,
  "SPX/USDT:USDT": 1.2486,
  "STX/USDT:USDT": 0.6612,
  "SUI/USDT:USDT": 2.7874,
  "TAO/USDT:USDT": 333.1,
  "TIA/USDT:USDT": 1.449,
  "TRUMP/USDT:USDT": 0.1254,
  "TRX/USDT:USDT": 0.27599,
  "ZETA/USDT:USDT": 0.1755,
  "ZRO/USDT:USDT": 1.789
}