{
  "AAVE/USDT:USDT": 248.59,
  "ADA/USDT:USDT": 0.6569,
  "AI16Z/USDT:USDT": 0.2083,
  "AIXBT/USDT:USDT": 0.17889,
  "ALGO/USDT:USDT": 0.1881,
  "APT/USDT:USDT": 4.6361,
  "ARB/USDT:USDT": 0.3355,
  "AR/USDT:USDT": 6.08,
  "ATOM/USDT:USDT": 4.173,
  "AVAX/USDT:USDT": 19.457,
  "BCH/USDT:USDT": 386.98,
  "BERA/USDT:USDT": 2.336,
  "BNB/USDT:USDT": 647.86,
  "CRV/USDT:USDT": 0.6285,
  "DOGE/USDT:USDT": 0.17776,
  "DOT/USDT:USDT": 3.931,
  "EIGEN/USDT:USDT": 1.4061,
  "ENA/USDT:USDT": 0.2976,
  "ETC/USDT:USDT": 16.601,
  "ETH/USDT:USDT": 2476.45,
  "FARTCOIN/USDT:USDT": 1.0549,
  "FLOKI/USDT:USDT": 8.529e-05,
  "FXS/USDT:USDT": 2.786,
  "GOAT/USDT:USDT": 0.1158,
  "GRASS/USDT:USDT": 2.0214,
  "HBAR/USDT:USDT": 0.16547,
  "HYPE/USDT:USDT": 34.57,
  "INJ/USDT:USDT": 11.892,
  "IP/USDT:USDT": 4.01,
  "JTO/USDT:USDT": 1.8025,
  "JUP/USDT:USDT": 0.4675,
  "KAITO/USDT:USDT": 1.7047,
  "LDO/USDT:USDT": 0.7769,
  "LINK/USDT:USDT": 13.247,
  "LTC/USDT:USDT": 85.13,
  "MEW/USDT:USDT": 0.003063,
  "MKR/USDT:USDT": 1759.8,
  "MOODENG/USDT:USDT": 0.19095,
  "MOVE/USDT:USDT": 0.1373,
  "NEAR/USDT:USDT": 2.305,
  "ONDO/USDT:USDT": 0.8046,
  "OP/USDT:USDT": 0.5976,
  "ORDI/USDT:USDT": 8.237,
  "PENDLE/USDT:USDT": 4.0237,
  "PENGU/USDT:USDT": 0.00954,
  "PEPE/USDT:USDT": 1.1129e-05,
  "PNUT/USDT:USDT": 0.2484,
  "POL/USDT:USDT": 0.20795,
  "POPCAT/USDT:USDT": 0.3561,
  "RENDER/USDT:USDT": 3.753,
  "RUNE/USDT:USDT": 1.601,
  "SEI/USDT:USDT": 0.1873,
  "SHIB/USDT:USDT": 1.2552e-05,
  "SOL/USDT:USDT": 150.79,
  "SPX/USDT:USDT": 1.1056,
  "STX/USDT:USDT": 0.6608,
  "SUI/USDT:USDT": 3.1483,
  "TAO/USDT:USDT": 369.3,
  "TIA/USDT:USDT": 2.036,
  "TRUMP/USDT:USDT": 0.1614,
  "TRX/USDT:USDT": 0.27829,
  "ZETA/USDT:USDT": 0.2086,
  "ZRO/USDT:USDT": 2.188
}