{
  "AAVE/USDT:USDT": 265.19,
  "ADA/USDT:USDT": 0.6722,
  "AI16Z/USDT:USDT": 0.2163,
  "AIXBT/USDT:USDT": 0.17689,
  "ALGO/USDT:USDT": 0.1923,
  "APT/USDT:USDT": 4.8305,
  "ARB/USDT:USDT": 0.3625,
  "AR/USDT:USDT": 6.524,
  "ATOM/USDT:USDT": 4.301,
  "AVAX/USDT:USDT": 20.412,
  "BCH/USDT:USDT": 401.81,
  "BERA/USDT:USDT": 2.457,
  "BNB/USDT:USDT": 666.0,
  "CRV/USDT:USDT": 0.6567,
  "DOGE/USDT:USDT": 0.18998,
  "DOT/USDT:USDT": 4.036,
  "EIGEN/USDT:USDT": 1.5222,
  "ENA/USDT:USDT": 0.3191,
  "ETC/USDT:USDT": 17.341,
  "ETH/USDT:USDT": 2621.07,
  "FARTCOIN/USDT:USDT": 0.9762,
  "FLOKI/USDT:USDT": 8.313e-05,
  "FXS/USDT:USDT": 2.991,
  "GOAT/USDT:USDT": 0.12173,
  "GRASS/USDT:USDT": 1.9399,
  "HBAR/USDT:USDT": 0.16807,
  "HYPE/USDT:USDT": 35.47,
  "INJ/USDT:USDT": 12.377,
  "IP/USDT:USDT": 4.053,
  "JTO/USDT:USDT": 1.866,
  "JUP/USDT:USDT": 0.5271,
  "KAITO/USDT:USDT": 1.6784,
  "LDO/USDT:USDT": 0.9033,
  "LINK/USDT:USDT": 13.912,
  "LTC/USDT:USDT": 88.5,
  "MEW/USDT:USDT": 0.003228,
  "MKR/USDT:USDT": 1785.6,
  "MOODENG/USDT:USDT": 0.1967,
  "MOVE/USDT:USDT": 0.1448,
  "NEAR/USDT:USDT": 2.471,
  "ONDO/USDT:USDT": 0.8368,
  "OP/USDT:USDT": 0.636,
  "ORDI/USDT:USDT": 8.823,
  "PENDLE/USDT:USDT": 4.1569,
  "PENGU/USDT:USDT": 0.01015,
  "PEPE/USDT:USDT": 1.2024e-05,
  "PNUT/USDT:USDT": 0.2603,
  "POL/USDT:USDT": 0.21433,
  "POPCAT/USDT:USDT": 0.3546,
  "RENDER/USDT:USDT": 3.798,
  "RUNE/USDT:USDT": 1.634,
  "SEI/USDT:USDT": 0.195,
  "SHIB/USDT:USDT": 1.2886e-05,
  "SOL/USDT:USDT": 155.37,
  "SPX/USDT:USDT": 1.1409,
  "STX/USDT:USDT": 0.7592,
  "SUI/USDT:USDT": 3.2046,
  "TAO/USDT:USDT": 381.9,
  "TIA/USDT:USDT": 2.171,
  "TRUMP/USDT:USDT": 0.1726,
  "TRX/USDT:USDT": 0.27337,
  "ZETA/USDT:USDT": 0.2193,
  "ZRO/USDT:USDT": 2.23
}