{
  "AAVE/USDT:USDT": 290.75,
  "ADA/USDT:USDT": 0.7905,
  "AI16Z/USDT:USDT": 0.1358,
  "AIXBT/USDT:USDT": 0.12757,
  "ALGO/USDT:USDT": 0.2664,
  "APT/USDT:USDT": 4.6621,
  "ARB/USDT:USDT": 0.4343,
  "AR/USDT:USDT": 7.467,
  "ATOM/USDT:USDT": 4.605,
  "AVAX/USDT:USDT": 23.8,
  "BCH/USDT:USDT": 585.11,
  "BERA/USDT:USDT": 2.018,
  "BNB/USDT:USDT": 793.51,
  "CRV/USDT:USDT": 0.9505,
  "DOGE/USDT:USDT": 0.23023,
  "DOT/USDT:USDT": 3.978,
  "EIGEN/USDT:USDT": 1.3148,
  "ENA/USDT:USDT": 0.6455,
  "ETC/USDT:USDT": 22.395,
  "ETH/USDT:USDT": 4011.65,
  "FARTCOIN/USDT:USDT": 1.038,
  "FLOKI/USDT:USDT": 0.00011856,
  "FXS/USDT:USDT": 3.176,
  "GOAT/USDT:USDT": 0.10041,
  "GRASS/USDT:USDT": 0.7387,
  "HBAR/USDT:USDT": 0.26153,
  "HYPE/USDT:USDT": 40.62,
  "INJ/USDT:USDT": 14.085,
  "IP/USDT:USDT": 6.485,
  "JTO/USDT:USDT": 1.8247,
  "JUP/USDT:USDT": 0.4975,
  "KAITO/USDT:USDT": 1.1943,
  "LDO/USDT:USDT": 1.1281,
  "LINK/USDT:USDT": 19.935,
  "LTC/USDT:USDT": 123.78,
  "MEW/USDT:USDT": 0.003228,
  "MKR/USDT:USDT": 2016.4,
  "MOODENG/USDT:USDT": 0.17178,
  "MOVE/USDT:USDT": 0.1406,
  "NEAR/USDT:USDT": 2.709,
  "ONDO/USDT:USDT": 1.0174,
  "OP/USDT:USDT": 0.7605,
  "ORDI/USDT:USDT": 9.771,
  "PENDLE/USDT:USDT": 5.3997,
  "PENGU/USDT:USDT": 0.03746,
  "PEPE/USDT:USDT": 1.1737e-05,
  "PNUT/USDT:USDT": 0.2373,
  "POL/USDT:USDT": 0.24768,
  "POPCAT/USDT:USDT": 0.323,
  "RENDER/USDT:USDT": 3.853,
  "RUNE/USDT:USDT": 1.398,
  "SEI/USDT:USDT": 0.3133,
  "SHIB/USDT:USDT": 1.321e-05,
  "SOL/USDT:USDT": 176.79,
  "SPX/USDT:USDT": 1.7783,
  "STX/USDT:USDT": 0.7359,
  "SUI/USDT:USDT": 3.8308,
  "TAO/USDT:USDT": 373.0,
  "TIA/USDT:USDT": 1.758,
  "TRUMP/USDT:USDT": 0.1497,
  "TRX/USDT:USDT": 0.33864,
  "ZETA/USDT:USDT": 0.1998,
  "ZRO/USDT:USDT": 1.87
}