{
  "AAVE/USDT:USDT": 275.25,
  "ADA/USDT:USDT": 0.7668,
  "AI16Z/USDT:USDT": 0.1307,
  "AIXBT/USDT:USDT": 0.1288,
  "ALGO/USDT:USDT": 0.2593,
  "APT/USDT:USDT": 4.3406,
  "ARB/USDT:USDT": 0.4091,
  "AR/USDT:USDT": 6.98,
  "ATOM/USDT:USDT": 4.404,
  "AVAX/USDT:USDT": 22.743,
  "BCH/USDT:USDT": 576.11,
  "BERA/USDT:USDT": 1.9,
  "BNB/USDT:USDT": 776.26,
  "CRV/USDT:USDT": 0.9361,
  "DOGE/USDT:USDT": 0.21424,
  "DOT/USDT:USDT": 3.791,
  "EIGEN/USDT:USDT": 1.223,
  "ENA/USDT:USDT": 0.6362,
  "ETC/USDT:USDT": 21.079,
  "ETH/USDT:USDT": 3842.26,
  "FARTCOIN/USDT:USDT": 0.9937,
  "FLOKI/USDT:USDT": 0.00011188,
  "FXS/USDT:USDT": 2.807,
  "GOAT/USDT:USDT": 0.10041,
  "GRASS/USDT:USDT": 0.6925,
  "HBAR/USDT:USDT": 0.25275,
  "HYPE/USDT:USDT": 39.01,
  "INJ/USDT:USDT": 13.647,
  "IP/USDT:USDT": 6.183,
  "JTO/USDT:USDT": 1.7632,
  "JUP/USDT:USDT": 0.4928,
  "KAITO/USDT:USDT": 1.1572,
  "LDO/USDT:USDT": 1.0105,
  "LINK/USDT:USDT": 17.607,
  "LTC/USDT:USDT": 120.19,
  "MEW/USDT:USDT": 0.003176,
  "MKR/USDT:USDT": 1987.9,
  "MOODENG/USDT:USDT": 0.1639,
  "MOVE/USDT:USDT": 0.1345,
  "NEAR/USDT:USDT": 2.596,
  "ONDO/USDT:USDT": 0.9829,
  "OP/USDT:USDT": 0.702,
  "ORDI/USDT:USDT": 9.629,
  "PENDLE/USDT:USDT": 4.409,
  "PENGU/USDT:USDT": 0.03672,
  "PEPE/USDT:USDT": 1.0831e-05,
  "PNUT/USDT:USDT": 0.2353,
  "POL/USDT:USDT": 0.23858,
  "POPCAT/USDT:USDT": 0.3155,
  "RENDER/USDT:USDT": 3.725,
  "RUNE/USDT:USDT": 1.338,
  "SEI/USDT:USDT": 0.3051,
  "SHIB/USDT:USDT": 1.2653e-05,
  "SOL/USDT:USDT": 172.18,
  "SPX/USDT:USDT": 1.761,
  "STX/USDT:USDT": 0.7202,
  "SUI/USDT:USDT": 3.7498,
  "TAO/USDT:USDT": 357.5,
  "TIA/USDT:USDT": 1.732,
  "TRUMP/USDT:USDT": 0.1468,
  "TRX/USDT:USDT": 0.33877,
  "ZETA/USDT:USDT": 0.1918,
  "ZRO/USDT:USDT": 1.85
}