{
  "AAVE/USDT:USDT": 259.84,
  "ADA/USDT:USDT": 0.5954,
  "AI16Z/USDT:USDT": 0.1644,
  "AIXBT/USDT:USDT": 0.14673,
  "ALGO/USDT:USDT": 0.1687,
  "APT/USDT:USDT": 4.364,
  "ARB/USDT:USDT": 0.2985,
  "AR/USDT:USDT": 5.313,
  "ATOM/USDT:USDT": 3.997,
  "AVAX/USDT:USDT": 18.413,
  "BCH/USDT:USDT": 464.32,
  "BERA/USDT:USDT": 1.853,
  "BNB/USDT:USDT": 640.82,
  "CRV/USDT:USDT": 0.5848,
  "DOGE/USDT:USDT": 0.16794,
  "DOT/USDT:USDT": 3.637,
  "EIGEN/USDT:USDT": 1.1701,
  "ENA/USDT:USDT": 0.2769,
  "ETC/USDT:USDT": 16.268,
  "ETH/USDT:USDT": 2507.83,
  "FARTCOIN/USDT:USDT": 1.1179,
  "FLOKI/USDT:USDT": 7.277e-05,
  "FXS/USDT:USDT": 2.416,
  "GOAT/USDT:USDT": 0.09501,
  "GRASS/USDT:USDT": 1.4043,
  "HBAR/USDT:USDT": 0.14696,
  "HYPE/USDT:USDT": 39.35,
  "INJ/USDT:USDT": 10.749,
  "IP/USDT:USDT": 2.771,
  "JTO/USDT:USDT": 2.1532,
  "JUP/USDT:USDT": 0.394,
  "KAITO/USDT:USDT": 1.3375,
  "LDO/USDT:USDT": 0.7609,
  "LINK/USDT:USDT": 12.892,
  "LTC/USDT:USDT": 84.87,
  "MEW/USDT:USDT": 0.002629,
  "MKR/USDT:USDT": 1995.7,
  "MOODENG/USDT:USDT": 0.14642,
  "MOVE/USDT:USDT": 0.1322,
  "NEAR/USDT:USDT": 2.128,
  "ONDO/USDT:USDT": 0.7421,
  "OP/USDT:USDT": 0.5526,
  "ORDI/USDT:USDT": 7.425,
  "PENDLE/USDT:USDT": 3.7228,
  "PENGU/USDT:USDT": 0.00914,
  "PEPE/USDT:USDT": 1.0073e-05,
  "PNUT/USDT:USDT": 0.2135,
  "POL/USDT:USDT": 0.18974,
  "POPCAT/USDT:USDT": 0.2875,
  "RENDER/USDT:USDT": 3.169,
  "RUNE/USDT:USDT": 1.416,
  "SEI/USDT:USDT": 0.1677,
  "SHIB/USDT:USDT": 1.1603e-05,
  "SOL/USDT:USDT": 145.54,
  "SPX/USDT:USDT": 1.3444,
  "STX/USDT:USDT": 0.6058,
  "SUI/USDT:USDT": 2.777,
  "TAO/USDT:USDT": 346.9,
  "TIA/USDT:USDT": 1.666,
  "TRUMP/USDT:USDT": 0.1404,
  "TRX/USDT:USDT": 0.26978,
  "ZETA/USDT:USDT": 0.1823,
  "ZRO/USDT:USDT": 1.842
}