{
  "AAVE/USDT:USDT": 272.84,
  "ADA/USDT:USDT": 0.7587,
  "AI16Z/USDT:USDT": 0.1392,
  "AIXBT/USDT:USDT": 0.13057,
  "ALGO/USDT:USDT": 0.2521,
  "APT/USDT:USDT": 4.4615,
  "ARB/USDT:USDT": 0.4116,
  "AR/USDT:USDT": 7.267,
  "ATOM/USDT:USDT": 4.394,
  "AVAX/USDT:USDT": 23.157,
  "BCH/USDT:USDT": 567.76,
  "BERA/USDT:USDT": 1.968,
  "BNB/USDT:USDT": 785.2,
  "CRV/USDT:USDT": 1.0352,
  "DOGE/USDT:USDT": 0.21738,
  "DOT/USDT:USDT": 3.769,
  "EIGEN/USDT:USDT": 1.2498,
  "ENA/USDT:USDT": 0.597,
  "ETC/USDT:USDT": 21.207,
  "ETH/USDT:USDT": 3762.28,
  "FARTCOIN/USDT:USDT": 1.0547,
  "FLOKI/USDT:USDT": 0.00011188,
  "FXS/USDT:USDT": 3.143,
  "GOAT/USDT:USDT": 0.10346,
  "GRASS/USDT:USDT": 0.8021,
  "HBAR/USDT:USDT": 0.2544,
  "HYPE/USDT:USDT": 42.22,
  "INJ/USDT:USDT": 13.774,
  "IP/USDT:USDT": 5.918,
  "JTO/USDT:USDT": 1.816,
  "JUP/USDT:USDT": 0.5158,
  "KAITO/USDT:USDT": 1.2183,
  "LDO/USDT:USDT": 1.0249,
  "LINK/USDT:USDT": 17.48,
  "LTC/USDT:USDT": 109.52,
  "MEW/USDT:USDT": 0.003204,
  "MKR/USDT:USDT": 2024.5,
  "MOODENG/USDT:USDT": 0.17482,
  "MOVE/USDT:USDT": 0.1388,
  "NEAR/USDT:USDT": 2.62,
  "ONDO/USDT:USDT": 0.9425,
  "OP/USDT:USDT": 0.6995,
  "ORDI/USDT:USDT": 9.628,
  "PENDLE/USDT:USDT": 4.3761,
  "PENGU/USDT:USDT": 0.03534,
  "PEPE/USDT:USDT": 1.1194e-05,
  "PNUT/USDT:USDT": 0.251,
  "POL/USDT:USDT": 0.21592,
  "POPCAT/USDT:USDT": 0.3267,
  "RENDER/USDT:USDT": 3.809,
  "RUNE/USDT:USDT": 1.375,
  "SEI/USDT:USDT": 0.3126,
  "SHIB/USDT:USDT": 1.2711e-05,
  "SOL/USDT:USDT": 175.75,
  "SPX/USDT:USDT": 1.8361,
  "STX/USDT:USDT": 0.7471,
  "SUI/USDT:USDT": 3.7465,
  "TAO/USDT:USDT": 369.1,
  "TIA/USDT:USDT": 1.759,
  "TRUMP/USDT:USDT": 0.1509,
  "TRX/USDT:USDT": 0.32744,
  "ZETA/USDT:USDT": 0.1988,
  "ZRO/USDT:USDT": 1.801
}