{
  "AAVE/USDT:USDT": 273.06,
  "ADA/USDT:USDT": 0.6198,
  "AI16Z/USDT:USDT": 0.1753,
  "AIXBT/USDT:USDT": 0.16021,
  "ALGO/USDT:USDT": 0.1723,
  "APT/USDT:USDT": 4.5176,
  "ARB/USDT:USDT": 0.3094,
  "AR/USDT:USDT": 5.642,
  "ATOM/USDT:USDT": 4.079,
  "AVAX/USDT:USDT": 18.821,
  "BCH/USDT:USDT": 472.5,
  "BERA/USDT:USDT": 1.975,
  "BNB/USDT:USDT": 648.82,
  "CRV/USDT:USDT": 0.5892,
  "DOGE/USDT:USDT": 0.17087,
  "DOT/USDT:USDT": 3.758,
  "EIGEN/USDT:USDT": 1.202,
  "ENA/USDT:USDT": 0.2859,
  "ETC/USDT:USDT": 16.7,
  "ETH/USDT:USDT": 2532.28,
  "FARTCOIN/USDT:USDT": 1.1469,
  "FLOKI/USDT:USDT": 7.476e-05,
  "FXS/USDT:USDT": 2.505,
  "GOAT/USDT:USDT": 0.09963,
  "GRASS/USDT:USDT": 1.4654,
  "HBAR/USDT:USDT": 0.15126,
  "HYPE/USDT:USDT": 40.88,
  "INJ/USDT:USDT": 11.324,
  "IP/USDT:USDT": 3.334,
  "JTO/USDT:USDT": 2.2153,
  "JUP/USDT:USDT": 0.4046,
  "KAITO/USDT:USDT": 1.4316,
  "LDO/USDT:USDT": 0.7968,
  "LINK/USDT:USDT": 13.208,
  "LTC/USDT:USDT": 84.89,
  "MEW/USDT:USDT": 0.00273,
  "MKR/USDT:USDT": 2076.7,
  "MOODENG/USDT:USDT": 0.15013,
  "MOVE/USDT:USDT": 0.138,
  "NEAR/USDT:USDT": 2.18,
  "ONDO/USDT:USDT": 0.7512,
  "OP/USDT:USDT": 0.5691,
  "ORDI/USDT:USDT": 7.725,
  "PENDLE/USDT:USDT": 3.9882,
  "PENGU/USDT:USDT": 0.00954,
  "PEPE/USDT:USDT": 1.0199e-05,
  "PNUT/USDT:USDT": 0.2268,
  "POL/USDT:USDT": 0.19815,
  "POPCAT/USDT:USDT": 0.3023,
  "RENDER/USDT:USDT": 3.283,
  "RUNE/USDT:USDT": 1.463,
  "SEI/USDT:USDT": 0.1711,
  "SHIB/USDT:USDT": 1.17e-05,
  "SOL/USDT:USDT": 149.25,
  "SPX/USDT:USDT": 1.4115,
  "STX/USDT:USDT": 0.6172,
  "SUI/USDT:USDT": 2.8941,
  "TAO/USDT:USDT": 350.7,
  "TIA/USDT:USDT": 1.669,
  "TRUMP/USDT:USDT": 0.1412,
  "TRX/USDT:USDT": 0.27322,
  "ZETA/USDT:USDT": 0.1881,
  "ZRO/USDT:USDT": 1.859
}