{
  "AAVE/USDT:USDT": 249.34,
  "ADA/USDT:USDT": 0.5628,
  "AI16Z/USDT:USDT": 0.1517,
  "AIXBT/USDT:USDT": 0.13734,
  "ALGO/USDT:USDT": 0.1727,
  "APT/USDT:USDT": 4.1862,
  "ARB/USDT:USDT": 0.2955,
  "AR/USDT:USDT": 5.165,
  "ATOM/USDT:USDT": 3.981,
  "AVAX/USDT:USDT": 17.688,
  "BCH/USDT:USDT": 456.66,
  "BERA/USDT:USDT": 1.726,
  "BNB/USDT:USDT": 633.12,
  "CRV/USDT:USDT": 0.567,
  "DOGE/USDT:USDT": 0.15925,
  "DOT/USDT:USDT": 3.344,
  "EIGEN/USDT:USDT": 1.1138,
  "ENA/USDT:USDT": 0.2578,
  "ETC/USDT:USDT": 16.102,
  "ETH/USDT:USDT": 2348.98,
  "FARTCOIN/USDT:USDT": 1.0342,
  "FLOKI/USDT:USDT": 7e-05,
  "FXS/USDT:USDT": 2.286,
  "GOAT/USDT:USDT": 0.09567,
  "GRASS/USDT:USDT": 1.1743,
  "HBAR/USDT:USDT": 0.1453,
  "HYPE/USDT:USDT": 37.86,
  "INJ/USDT:USDT": 10.409,
  "IP/USDT:USDT": 3.177,
  "JTO/USDT:USDT": 2.1298,
  "JUP/USDT:USDT": 0.3763,
  "KAITO/USDT:USDT": 1.3671,
  "LDO/USDT:USDT": 0.6946,
  "LINK/USDT:USDT": 12.375,
  "LTC/USDT:USDT": 83.92,
  "MEW/USDT:USDT": 0.002529,
  "MKR/USDT:USDT": 2013.1,
  "MOODENG/USDT:USDT": 0.1461,
  "MOVE/USDT:USDT": 0.1629,
  "NEAR/USDT:USDT": 2.071,
  "ONDO/USDT:USDT": 0.724,
  "OP/USDT:USDT": 0.5341,
  "ORDI/USDT:USDT": 7.158,
  "PENDLE/USDT:USDT": 3.4345,
  "PENGU/USDT:USDT": 0.00923,
  "PEPE/USDT:USDT": 9.543e-06,
  "PNUT/USDT:USDT": 0.2133,
  "POL/USDT:USDT": 0.17744,
  "POPCAT/USDT:USDT": 0.289,
  "RENDER/USDT:USDT": 3.003,
  "RUNE/USDT:USDT": 1.332,
  "SEI/USDT:USDT": 0.2281,
  "SHIB/USDT:USDT": 1.1292e-05,
  "SOL/USDT:USDT": 141.62,
  "SPX/USDT:USDT": 1.2128,
  "STX/USDT:USDT": 0.6084,
  "SUI/USDT:USDT": 2.7158,
  "TAO/USDT:USDT": 337.3,
  "TIA/USDT:USDT": 1.522,
  "TRUMP/USDT:USDT": 0.1224,
  "TRX/USDT:USDT": 0.27224,
  "ZETA/USDT:USDT": 0.1743,
  "ZRO/USDT:USDT": 1.707
}